[
  {
    "RepositoryName": "incubator-brpc-website",
    "OwnerName": "apache",
    "BeginDate": "2019-09-26T04:04:34Z",
    "EndDate": "2019-09-26T05:04:34",
    "Branches": 2,
    "Forks": 2,
    "Files": [
      {
        "Sha": "7c9babcdb9e52d074a9b062067b71017b702dec6",
        "FileName": "README.md",
        "Path": "README.md",
        "DateUpdated": "2019-09-26T04:52:11Z",
        "Additions": 2,
        "Deletions": 4,
        "Commits": [
          "ca314c979bd6702e69b59937d32f65aff94d0389",
          "45cbac2be62c8bc993575a3f98423ee9cc96cf92"
        ]
      },
      {
        "Sha": "e38ca2bfc8b1889b94eba2ae89935621a555627e",
        "FileName": "_navigation.html",
        "Path": "_includes/themes/apache/_navigation.html",
        "DateUpdated": "2019-09-26T04:52:11Z",
        "Additions": 1,
        "Deletions": 0,
        "Commits": [
          "ca314c979bd6702e69b59937d32f65aff94d0389",
          "0d21c30a36ef60d091078c4362c6ea73a82c9c1e"
        ]
      },
      {
        "Sha": "deaaf055893713c6ca752107b160f93d8f91fb15",
        "FileName": "README.md",
        "Path": "README.md",
        "DateUpdated": "2019-09-26T04:30:25Z",
        "Additions": 8,
        "Deletions": 2,
        "Commits": [
          "8a4b5ada9583cfe7b9ae718f24aa480823c94156",
          "bcd151e0e898e4d3fd270e59429a18bb35136596"
        ]
      }
    ],
    "Commits": [
      {
        "sha": "ca314c979bd6702e69b59937d32f65aff94d0389",
        "Author": {
          "name": "\"tanzhongyi\"",
          "location": "beijing,china",
          "company": "baidu.com"
        },
        "Commitor": {
          "name": "\"GitHub Web Flow\""
        },
        "Date": "2019-09-26T04:52:11Z",
        "additions": 3,
        "deletions": 2,
        "files": [
          "7c9babcdb9e52d074a9b062067b71017b702dec6",
          "e38ca2bfc8b1889b94eba2ae89935621a555627e"
        ]
      },
      {
        "sha": "45cbac2be62c8bc993575a3f98423ee9cc96cf92",
        "Author": {
          "name": "\"tanzhongyi\"",
          "location": "beijing,china",
          "company": "baidu.com"
        },
        "Commitor": {
          "name": "\"tanzhongyi\"",
          "location": "beijing,china",
          "company": "baidu.com"
        },
        "Date": "2019-09-26T04:49:25Z",
        "additions": 2,
        "deletions": 2,
        "files": [
          "7c9babcdb9e52d074a9b062067b71017b702dec6"
        ]
      },
      {
        "sha": "0d21c30a36ef60d091078c4362c6ea73a82c9c1e",
        "Author": {
          "name": "\"tanzhongyi\"",
          "location": "beijing,china",
          "company": "baidu.com"
        },
        "Commitor": {
          "name": "\"tanzhongyi\"",
          "location": "beijing,china",
          "company": "baidu.com"
        },
        "Date": "2019-09-26T04:37:08Z",
        "additions": 1,
        "deletions": 0,
        "files": [
          "e38ca2bfc8b1889b94eba2ae89935621a555627e"
        ]
      },
      {
        "sha": "8a4b5ada9583cfe7b9ae718f24aa480823c94156",
        "Author": {
          "name": "\"tanzhongyi\"",
          "location": "beijing,china",
          "company": "baidu.com"
        },
        "Commitor": {
          "name": "\"GitHub Web Flow\""
        },
        "Date": "2019-09-26T04:30:25Z",
        "additions": 8,
        "deletions": 1,
        "files": [
          "deaaf055893713c6ca752107b160f93d8f91fb15"
        ]
      },
      {
        "sha": "bcd151e0e898e4d3fd270e59429a18bb35136596",
        "Author": {
          "name": "\"tanzhongyi\"",
          "location": "beijing,china",
          "company": "baidu.com"
        },
        "Commitor": {
          "name": "\"tanzhongyi\"",
          "location": "beijing,china",
          "company": "baidu.com"
        },
        "Date": "2019-09-26T04:29:19Z",
        "additions": 8,
        "deletions": 1,
        "files": [
          "deaaf055893713c6ca752107b160f93d8f91fb15"
        ]
      }
    ]
  }
]